{
  "id": "2026-03-24-daily-report",
  "title": "#Learn&Digest：2026年3月24日 每日报告打卡",
  "date": "2026-03-24",
  "category": "daily",
  "categoryLabel": "每日报告打卡",
  "tags": [
    "每日报告",
    "AI生成",
    "学习打卡"
  ],
  "excerpt": "2026年3月24日 的每日阅读与报告打卡图片，共 4 张。",
  "images": {
    "cover": "01.jpg",
    "cards": [
      "02.jpg",
      "03.jpg",
      "04.jpg"
    ],
    "longForm": null
  },
  "author": "Renee",
  "readTime": "2 分钟",
  "sourceFiles": [
    "Gemini_Generated_Image_v7fol2v7fol2v7fo.png",
    "Gemini_Generated_Image_31q9ts31q9ts31q9.png",
    "Gemini_Generated_Image_bwqst9bwqst9bwqs.png",
    "Gemini_Generated_Image_pf1p1npf1p1npf1p.png"
  ]
}
